zkp_playground/__init__.py
zkp_playground/algorithms.py
zkp_playground/const.py
zkp_playground/structure.py
zkp_playground/utils.py
zkp_playground/algebra/__init__.py
zkp_playground/algebra/abstract.py
zkp_playground/algebra/concrete.py
zkp_playground/algebra/isomorphism.py
zkp_playground/algebra/meta.py
zkp_playground/algebra/rings.py
zkp_playground/algebra/utils.py
zkp_playground/algebra/fields/__init__.py
zkp_playground/algebra/fields/polyfield.py
zkp_playground/algebra/fields/primefield.py
zkp_playground/algebra/groups/__init__.py
zkp_playground/algebra/groups/cyclic_group.py
zkp_playground/algebra/groups/jacobian.py
zkp_playground/algebra/groups/ecg/__init__.py
zkp_playground/algebra/groups/ecg/elliptic.py
zkp_playground/algebra/rings/__init__.py
zkp_playground/algebra/rings/poly.py
zkp_playground/blockchain/__init__.py
zkp_playground/blockchain/bitcoin/__init__.py
zkp_playground/blockchain/bitcoin/address.py
zkp_playground/blockchain/bitcoin/const.py
zkp_playground/blockchain/bitcoin/private.py
zkp_playground/blockchain/bitcoin/public.py
zkp_playground/blockchain/bitcoin/sign.py
zkp_playground/blockchain/bitcoin/asn/__init__.py
zkp_playground/blockchain/bitcoin/asn/signature.py
zkp_playground/blockchain/eos/__init__.py
zkp_playground/blockchain/eos/address.py
zkp_playground/blockchain/eos/private.py
zkp_playground/blockchain/eos/public.py
zkp_playground/blockchain/ethereum/__init__.py
zkp_playground/blockchain/ethereum/address.py
zkp_playground/blockchain/ethereum/private.py
zkp_playground/blockchain/ethereum/public.py
zkp_playground/client/__init__.py
zkp_playground/client/shell.py
zkp_playground/crypto/MiMC.py
zkp_playground/crypto/__init__.py
zkp_playground/crypto/damgard_jurik.py
zkp_playground/crypto/elgamal.py
zkp_playground/crypto/paillier.py
zkp_playground/crypto/pkcs.py
zkp_playground/crypto/rsa.py
zkp_playground/crypto/sponge.py
zkp_playground/crypto/ssss.py
zkp_playground/crypto/vss.py
zkp_playground/crypto/ecdsa/__init__.py
zkp_playground-1.0.0.dist-info/LICENSE
zkp_playground-1.0.0.dist-info/METADATA
zkp_playground-1.0.0.dist-info/WHEEL
zkp_playground-1.0.0.dist-info/entry_points.txt
zkp_playground-1.0.0.dist-info/top_level.txt
zkp_playground-1.0.0.dist-info/RECORD
