Metadata-Version: 2.1
Name: zkp-playground
Version: 1.0.0
Summary: zkp-playground is a playground for ZKP algorithms.
Home-page: https://github.com/oxor-io/zkp-playground
Author: oxorio
Author-email: ping@oxor.io
License: GPL
Classifier: Development Status :: 5 - Production/Stable
Classifier: Environment :: Console
Classifier: Framework :: Jupyter
Classifier: Intended Audience :: Developers
Classifier: Intended Audience :: Education
Classifier: Intended Audience :: Science/Research
Classifier: License :: OSI Approved :: GNU General Public License (GPL)
Classifier: Operating System :: OS Independent
Classifier: Programming Language :: Python :: 3
Classifier: Programming Language :: Python :: 3.6
Classifier: Programming Language :: Python :: 3.7
Classifier: Programming Language :: Python :: 3.8
Classifier: Programming Language :: Python :: 3.9
Classifier: Programming Language :: Python :: 3.10
Classifier: Programming Language :: Python :: Implementation :: CPython
Classifier: Programming Language :: Python :: Implementation :: PyPy
Classifier: Topic :: Software Development
Classifier: Topic :: Software Development :: Libraries :: Python Modules
Classifier: Topic :: Security :: Cryptography
License-File: LICENSE
Requires-Dist: pyasn1 ==0.3.7
Requires-Dist: base58 ==0.2.5
Requires-Dist: asn1ate ==0.6.0
Requires-Dist: pysha3 ==1.0.2
Requires-Dist: flatbuffers ==1.12
